MANIFEST.in
README.md
README.rst
requirements.txt
setup.cfg
setup.py
flask_gridify/__init__.py
flask_gridify/utils.py
flask_gridify.egg-info/PKG-INFO
flask_gridify.egg-info/SOURCES.txt
flask_gridify.egg-info/dependency_links.txt
flask_gridify.egg-info/not-zip-safe
flask_gridify.egg-info/requires.txt
flask_gridify.egg-info/top_level.txt
flask_gridify/static/base.css
flask_gridify/static/grid.js
flask_gridify/static/thirdparty/bootstrap.min.css
flask_gridify/static/thirdparty/bootstrap.min.js
flask_gridify/static/thirdparty/jquery-3.4.1.min.js
flask_gridify/static/thirdparty/jsgrid/jsgrid-theme.min.css
flask_gridify/static/thirdparty/jsgrid/jsgrid.min.css
flask_gridify/static/thirdparty/jsgrid/jsgrid.min.js
flask_gridify/templates/gridify/base.html.jinja
flask_gridify/templates/gridify/grid.html.jinja
flask_gridify/templates/gridify/macros.html.jinja