Metadata-Version: 1.1
Name: flask-gridify
Version: 0.2.0
Summary: Automatically create editable grids in browser from SQLAlchemy models
Home-page: https://github.com/michaelsobczak/flask-gridify
Author: Michael Sobczak
Author-email: mikesobczak.code@gmail.com
License: MIT
Download-URL: https://github.com/michaelsobczak/flask-gridify/archive/0.1.0.tar.gz
Keywords: Flask,FlaskSQLAlchemy,FlaskRestless,jsgrid,data table
Platform: any
Classifier: Environment :: Web Environment
Classifier: Intended Audience :: Developers
Classifier: License :: OSI Approved :: BSD License
Classifier: Operating System :: OS Independent
Classifier: Programming Language :: Python
Classifier: Topic :: Internet :: WWW/HTTP :: Dynamic Content
Classifier: Topic :: Software Development :: Libraries :: Python Modules
